{
  "language_id": "fr",
  "words": [
    {"word": "j'ai une réservation", "romanization": "", "pronunciation_hint": "jé ün re-zer-va-syon", "meaning_de": "ich habe eine Reservierung", "meaning_en": "I have a reservation", "category": "phrasen", "frequency_rank": 1101, "concept_id": "i_have_reservation", "tone": null, "notes": "Hôtel"},
    {"word": "j'ai besoin d'un médecin", "romanization": "", "pronunciation_hint": "jé bə-zwɛ̃ dœ̃ med-sɛ̃", "meaning_de": "ich brauche einen Arzt", "meaning_en": "I need a doctor", "category": "koerper_gesundheit", "frequency_rank": 1102, "concept_id": "i_need_doctor", "tone": null, "notes": "Urgence"},
    {"word": "appelez la police", "romanization": "", "pronunciation_hint": "a-ple la po-lis", "meaning_de": "rufen Sie die Polizei", "meaning_en": "call the police", "category": "phrasen", "frequency_rank": 1103, "concept_id": "call_police", "tone": null, "notes": "Urgent"},
    {"word": "où est l'hôpital ?", "romanization": "", "pronunciation_hint": "u è lo-pi-tal", "meaning_de": "wo ist das Krankenhaus?", "meaning_en": "where is the hospital?", "category": "fragen_richtungen", "frequency_rank": 1104, "concept_id": "where_is_hospital", "tone": null, "notes": "Demander le chemin"},
    {"word": "j'ai perdu mon passeport", "romanization": "", "pronunciation_hint": "jé per-dü mon pas-por", "meaning_de": "ich habe meinen Pass verloren", "meaning_en": "I lost my passport", "category": "phrasen", "frequency_rank": 1105, "concept_id": "i_lost_passport", "tone": null, "notes": "Documents"},
    {"word": "puis-je payer par carte ?", "romanization": "", "pronunciation_hint": "pɥi-jə pe-yé par kart", "meaning_de": "kann ich mit Karte zahlen?", "meaning_en": "can I pay by card?", "category": "essen_trinken", "frequency_rank": 1106, "concept_id": "card_payment_question", "tone": null, "notes": "Paiement"}
  ]
}
